asyncio_pool/__init__.py
asyncio_pool/_pool.py
asyncio_pool/_typing.py
asyncio_pool/py.typed
asyncio_pool_ng-0.8.1.dist-info/LICENSE
asyncio_pool_ng-0.8.1.dist-info/METADATA
asyncio_pool_ng-0.8.1.dist-info/WHEEL
asyncio_pool_ng-0.8.1.dist-info/entry_points.txt
asyncio_pool_ng-0.8.1.dist-info/RECORD
