Metadata-Version: 2.1
Name: asyncio-pool-ng
Version: 0.8.1
Summary: A pool of coroutine functions.
Home-page: https://github.com/smithk86/asyncio-pool-ng
License: MIT
Author: Kyle Smith
Author-email: smithk86@smc3.com
Requires-Python: >=3.11,<4
Classifier: Framework :: AsyncIO
Classifier: Intended Audience :: Developers
Classifier: License :: OSI Approved :: MIT License
Classifier: Programming Language :: Python :: 3
Classifier: Programming Language :: Python :: 3.11
Classifier: Programming Language :: Python :: 3.12
Classifier: Topic :: Software Development :: Libraries :: Python Modules
Project-URL: Documentation, https://smithk86.github.io/asyncio-pool-ng
Project-URL: Repository, https://github.com/smithk86/asyncio-pool-ng
